{
  "slug": "nattributes",
  "name": "NATtributes",
  "icon": "https://creator-hub-prod.s3.us-east-2.amazonaws.com/ord-nattributes_pfp_1743323368952.gif",
  "description": "The First Generative DMT Art collection on Bitcoin. Art by DIDIMX and Anon Collaborator. Evolving art. About the project: https://medium.com/@satributesart/nattributes-a-new-dawn-for-digital-matter-and-bitcoin-292cdac4f8ce",
  "twitter_link": "https://twitter.com/satributes",
  "discord_link": "https://discord.gg/v3mV5SWqsW",
  "website_link": "https://satributes.art"
}