{
  "name": "UniSat Emblems",
  "supply": "5000",
  "icon": "https://next-cdn.unisat.io/static/2024/01/unisat-emblem-logo.png",
  "slug": "unisat-emblem",
  "description": "UniSat Emblems are a collection of commemorative emblems presented by UniSat to users in special circumstances. \nUniSat Emblem #1-#30 - Christmas Gift \nUniSat Emblem #31-#100 - 2024 New Year Gift \n - (to be expanded)",
  "twitter_link": "https://twitter.com/unisat_wallet",
  "discord_link": "https://discord.gg/EMskB2sMz8",
  "website_link": "https://unisat.io"
}
