{
  "slug": "the-golden-ratio",
  "name": "The Golden Ratio by Harto x Vivid Gallery",
  "icon": "https://creator-hub-prod.s3.us-east-2.amazonaws.com/ord-the-golden-ratio_pfp_1714731283781.png",
  "description": "420 generative artworks on Block 9 450x sats exploring the fibonacci pattern. Recursive & Parent/Child provenance. Art by Harto curated by VIVID Gallery.",
  "twitterLink": "https://twitter.com/vivid_ordinals",
  "discordLink": "https://discord.gg/dGzMHhmavc",
  "websiteLink": "https://www.vivid.gallery/generative/the-golden-ratio?utm_source=magiceden"
}