{
  "description": "These tiny Taproot Townies are just chillin' on the blockchain. Right now they live in a tiny world called The Nexus, just sign in with your wallet at LooperLands.io to begin your adventure! Added Bonus: Message me in Discord to get a copy of your custom sprite sheet allowing you to use your Bitcoin asset in other blockchain games! Even more utility coming soon...",
  "discord_link": "https://discord.gg/tPmqgszgku",
  "icon": "https://next-cdn.unisat.io/collection/logo/ord-taproot-townies.gif",
  "name": "Taproot Townies",
  "slug": "taproot-townies",
  "twitter_link": "https://x.com/m88nwalker",
  "website_link": "https://m88nlabs.com"
}